dreal/BUILD.bazel
dreal/__init__.py
dreal/_dreal_py.so
dreal/dreal.h
dreal/dreal_main.cc
dreal/dreal_main.h
dreal/dreal_py.cc
dreal/libdreal_.so
dreal/odr_test_module_py.cc
dreal/workspace.bzl
dreal/api/BUILD.bazel
dreal/api/api.cc
dreal/api/api.h
dreal/contractor/BUILD.bazel
dreal/contractor/contractor.cc
dreal/contractor/contractor.h
dreal/contractor/contractor_cell.cc
dreal/contractor/contractor_cell.h
dreal/contractor/contractor_fixpoint.cc
dreal/contractor/contractor_fixpoint.h
dreal/contractor/contractor_forall.h
dreal/contractor/contractor_ibex_fwdbwd.cc
dreal/contractor/contractor_ibex_fwdbwd.h
dreal/contractor/contractor_ibex_fwdbwd_mt.cc
dreal/contractor/contractor_ibex_fwdbwd_mt.h
dreal/contractor/contractor_ibex_polytope.cc
dreal/contractor/contractor_ibex_polytope.h
dreal/contractor/contractor_ibex_polytope_mt.cc
dreal/contractor/contractor_ibex_polytope_mt.h
dreal/contractor/contractor_id.cc
dreal/contractor/contractor_id.h
dreal/contractor/contractor_integer.cc
dreal/contractor/contractor_integer.h
dreal/contractor/contractor_join.cc
dreal/contractor/contractor_join.h
dreal/contractor/contractor_seq.cc
dreal/contractor/contractor_seq.h
dreal/contractor/contractor_status.cc
dreal/contractor/contractor_status.h
dreal/contractor/contractor_worklist_fixpoint.cc
dreal/contractor/contractor_worklist_fixpoint.h
dreal/contractor/counterexample_refiner.cc
dreal/contractor/counterexample_refiner.h
dreal/contractor/generic_contractor_generator.cc
dreal/contractor/generic_contractor_generator.h
dreal/dr/BUILD.bazel
dreal/dr/driver.cc
dreal/dr/driver.h
dreal/dr/parser.yy
dreal/dr/run.cc
dreal/dr/run.h
dreal/dr/scanner.h
dreal/dr/scanner.ll
dreal/examples/BUILD.bazel
dreal/examples/README.md
dreal/examples/check_lyapunov.cc
dreal/examples/control.cc
dreal/examples/control.h
dreal/examples/program_synthesis_abs.cc
dreal/examples/synthesize_lyapunov_damped_mathieu.cc
dreal/examples/synthesize_lyapunov_moore_greitzer.cc
dreal-4.21.6.2.dist-info/LICENSE
dreal-4.21.6.2.dist-info/METADATA
dreal-4.21.6.2.dist-info/WHEEL
dreal-4.21.6.2.dist-info/top_level.txt
dreal-4.21.6.2.dist-info/RECORD
