Metadata-Version: 2.1
Name: dreal
Version: 4.21.6.2
Summary: SMT Solver for Nonlinear Theories of Reals
Home-page: https://github.com/dreal/dreal4
Author: Soonho Kong
Author-email: soonho.kong@gmail.com
Project-URL: Bug Reports, https://github.com/dreal/dreal4/issues
Project-URL: Source, https://github.com/dreal/dreal4
Keywords: dreal,smt,theorem,prover
Classifier: License :: OSI Approved :: Apache Software License
Classifier: Programming Language :: Python :: 3
Classifier: Programming Language :: Python :: 3.7
Classifier: Programming Language :: Python :: 3.8
Classifier: Programming Language :: Python :: 3.9
Classifier: Programming Language :: Python :: 3.10
Classifier: Operating System :: POSIX :: Linux
Classifier: Operating System :: MacOS
License-File: LICENSE
